lazy/__init__.py
lazy/excel/__init__.py
lazy/excel/merge.py
lazy/toj/__init__.py
lazy/toj/reconciliation.py
lazy/toj/reconciliation_exper_processor.py
lazy/toj/reconciliation_packing.py
lazy/toj/reconciliation_rule.py
lazy/toj/reconciliation_source.py
lazy/toj/reconciliation_to_excel.py
lazy/toj/reconcilization_merge.py
lazy/toj/utils.py
slackoff_moo-1.0.8.dist-info/LICENSE
slackoff_moo-1.0.8.dist-info/METADATA
slackoff_moo-1.0.8.dist-info/WHEEL
slackoff_moo-1.0.8.dist-info/top_level.txt
slackoff_moo-1.0.8.dist-info/RECORD
